ilo_utils/__init__.py
ilo_utils/constants.py
ilo_utils/sweep.py
ilo_utils/utils.py
ilo_utils-0.3.0.dist-info/DESCRIPTION.rst
ilo_utils-0.3.0.dist-info/entry_points.txt
ilo_utils-0.3.0.dist-info/LICENSE.txt
ilo_utils-0.3.0.dist-info/METADATA
ilo_utils-0.3.0.dist-info/metadata.json
ilo_utils-0.3.0.dist-info/RECORD
ilo_utils-0.3.0.dist-info/top_level.txt
ilo_utils-0.3.0.dist-info/WHEEL
tests/__init__.py
tests/constants.py
